aioevt/__init__.py
aioevt/event.py
aioevt/manager.py
tests/__init__.py
tests/test_event.py
tests/test_manager.py
aioevt-2.2.1.dist-info/LICENSE
aioevt-2.2.1.dist-info/METADATA
aioevt-2.2.1.dist-info/WHEEL
aioevt-2.2.1.dist-info/top_level.txt
aioevt-2.2.1.dist-info/RECORD
